{
  "date": [null],
  "creator": null,
  "georeference_changed": null,
  "created": null,
  "image_url": "http://chartae-antiquae.cz/tiles/rajhrad/atlasy/3281002910857/3281002910857_02/ImageProperties.xml",
  "description": null,
  "scale": null,
  "external_id": "59061",
  "title": "mapa z atlasu \"Geographisch-historischer Atlas von Europa :\"",
  "collection_id": "c96b8290-8633-5c89-8aed-95da5c97814e",
  "is_reviewed": false,
  "contributor": null,
  "catalog_url": null,
  "viewer_url": null,
  "georeference_is_finished": true,
  "bounds": null,
  "reviewed": null,
  "publisher": null,
  "link_url": "http://chartae-antiquae.cz/maps/610",
  "id": "198de4fb-ca82-56f4-a373-a933bc452117",
  "physical_size": null,
  "dpi": null,
  "georefereces": {
    "cutline": [
      [
        3252,
        9564
      ],
      [
        11484,
        9508
      ],
      [
        11460,
        8076
      ],
      [
        13332,
        8124
      ],
      [
        13364,
        1852
      ],
      [
        4372,
        1884
      ],
      [
        4868,
        2908
      ],
      [
        4892,
        3740
      ],
      [
        3976,
        4700
      ],
      [
        3252,
        9564
      ]
    ],
    "created": "2015-02-08T07:53:42.997160+00:00",
    "transformation_method": "affine",
    "mapID": "198de4fb-ca82-56f4-a373-a933bc452117",
    "affine_transformation": null,
    "changed": "2021-09-13T14:51:00.968875+00:00",
    "gcps": [
      {
        "location": [
          11.5754815,
          48.1372719
        ],
        "pixel": [
          7609,
          6778
        ]
      },
      {
        "location": [
          2.3521334,
          48.8565056
        ],
        "pixel": [
          6321,
          6486
        ]
      },
      {
        "location": [
          -3.7035825,
          40.4167047
        ],
        "pixel": [
          5081,
          8020
        ]
      },
      {
        "location": [
          4.832005495,
          45.757717738
        ],
        "pixel": [
          6579,
          7168
        ]
      },
      {
        "location": [
          13.3888599,
          52.518163494
        ],
        "pixel": [
          7870,
          5866
        ]
      },
      {
        "location": [
          14.418509018,
          50.084796643
        ],
        "pixel": [
          7993,
          6398
        ]
      },
      {
        "location": [
          12.571445691,
          55.686664562
        ],
        "pixel": [
          7778,
          5206
        ]
      },
      {
        "location": [
          43.6825689012358,
          68.55919721241409
        ],
        "pixel": [
          10475,
          2216
        ]
      },
      {
        "location": [
          -5.396980878263348,
          35.893630757849394
        ],
        "pixel": [
          4623,
          8871
        ]
      },
      {
        "location": [
          1.6064757654883948,
          50.862695789559496
        ],
        "pixel": [
          6334,
          6050
        ]
      },
      {
        "location": [
          -4.519708541836629,
          54.239483716531254
        ],
        "pixel": [
          5743,
          5161
        ]
      },
      {
        "location": [
          -23.990058539510613,
          64.87349264917086
        ],
        "pixel": [
          4829,
          2319
        ]
      },
      {
        "location": [
          -20.155830023885613,
          66.11278164040115
        ],
        "pixel": [
          5250,
          2299
        ]
      },
      {
        "location": [
          -14.662665961385615,
          66.3739057357129
        ],
        "pixel": [
          5589,
          2395
        ]
      },
      {
        "location": [
          -22.57282221138562,
          63.84677716169972
        ],
        "pixel": [
          4836,
          2555
        ]
      },
      {
        "location": [
          34.520958497825085,
          35.62639761149413
        ],
        "pixel": [
          11292,
          9095
        ]
      },
      {
        "location": [
          8.922813966575093,
          44.43801008983891
        ],
        "pixel": [
          7106,
          7536
        ]
      },
      {
        "location": [
          50.21480261724647,
          44.5034298670206
        ],
        "pixel": [
          13136,
          6469
        ]
      },
      {
        "location": [
          28.984390674,
          41.017599319
        ],
        "pixel": [
          10207,
          8164
        ]
      },
      {
        "location": [
          30.312609613,
          59.939890001
        ],
        "pixel": [
          9695,
          4196
        ]
      },
      {
        "location": [
          -0.1276474,
          51.5073219
        ],
        "pixel": [
          6113,
          5850
        ]
      },
      {
        "location": [
          16.3725042,
          48.2083537
        ],
        "pixel": [
          8277,
          6818
        ]
      },
      {
        "location": [
          44.54366513147233,
          48.70289399380363
        ],
        "pixel": [
          12061,
          5973
        ]
      },
      {
        "location": [
          -9.253182050138347,
          32.55157930875704
        ],
        "pixel": [
          3847,
          9351
        ]
      },
      {
        "location": [
          -9.001739485820666,
          37.05372170989388
        ],
        "pixel": [
          4121,
          8452
        ]
      },
      {
        "location": [
          -5.600555484511605,
          50.10775956398828
        ],
        "pixel": [
          5336,
          5959
        ]
      },
      {
        "location": [
          -9.793146041836629,
          51.48815313493884
        ],
        "pixel": [
          4909,
          5509
        ]
      },
      {
        "location": [
          -9.903009323086629,
          52.58963131023549
        ],
        "pixel": [
          4988,
          5256
        ]
      },
      {
        "location": [
          -7.3541811980866285,
          55.372803174196775
        ],
        "pixel": [
          5480,
          4837
        ]
      },
      {
        "location": [
          -1.3286526699893149,
          59.8879314564706
        ],
        "pixel": [
          6387,
          4109
        ]
      },
      {
        "location": [
          -13.651923773885615,
          64.99915271618556
        ],
        "pixel": [
          5578,
          2761
        ]
      },
      {
        "location": [
          -23.144111273885613,
          66.34306612604138
        ],
        "pixel": [
          5093,
          2076
        ]
      },
      {
        "location": [
          12.673552408721985,
          67.71840865188392
        ],
        "pixel": [
          7916,
          2652
        ]
      },
      {
        "location": [
          26.67013443997199,
          70.95307019206365
        ],
        "pixel": [
          8959,
          1976
        ]
      },
      {
        "location": [
          10.592735841575111,
          57.74837485705058
        ],
        "pixel": [
          7622,
          4766
        ]
      },
      {
        "location": [
          26.237267091575088,
          35.23251167622196
        ],
        "pixel": [
          9901,
          9447
        ]
      },
      {
        "location": [
          9.362267091575092,
          42.99290996288235
        ],
        "pixel": [
          7181,
          7848
        ]
      },
      {
        "location": [
          43.777950242888934,
          66.19045032310777
        ],
        "pixel": [
          10587,
          2639
        ]
      }
    ]
  },
  "pubdate": ["1838"]
}