{
  "date": [null],
  "creator": null,
  "georeference_changed": null,
  "created": null,
  "image_url": "https://www.chartae-antiquae.cz/tiles/ntm/mapy/3129_060/ImageProperties.xml",
  "description": null,
  "scale": null,
  "external_id": "37728",
  "title": "Generální mapa okresních hejtmanství",
  "collection_id": "ce112fe9-4942-5c37-8f3c-3a397ab0c99b",
  "is_reviewed": false,
  "contributor": null,
  "catalog_url": null,
  "viewer_url": null,
  "georeference_is_finished": true,
  "bounds": [
    14.761304,
    50.01194,
    15.565161,
    50.382874
  ],
  "reviewed": null,
  "publisher": null,
  "link_url": "http://chartae-antiquae.cz/maps/37728",
  "id": "881e4590-cad8-587b-ac11-b5b236e75604",
  "physical_size": null,
  "dpi": null,
  "georefereces": {
    "cutline": [
      [
        677,
        449
      ],
      [
        4390,
        450
      ],
      [
        4394,
        1126
      ],
      [
        6832,
        1130
      ],
      [
        6830,
        4908
      ],
      [
        686,
        4908
      ],
      [
        677,
        449
      ]
    ],
    "created": "2017-01-30T01:40:22.196150+00:00",
    "transformation_method": "affine",
    "mapID": "881e4590-cad8-587b-ac11-b5b236e75604",
    "affine_transformation": null,
    "changed": "2017-01-30T01:40:22.196150+00:00",
    "gcps": [
      {
        "location": [
          15.1187588,
          50.142686
        ],
        "pixel": [
          3446,
          3346
        ]
      },
      {
        "location": [
          14.837046146,
          50.252057177
        ],
        "pixel": [
          1170,
          2024
        ]
      },
      {
        "location": [
          15.193071842,
          50.164386387
        ],
        "pixel": [
          4003,
          3089
        ]
      },
      {
        "location": [
          15.391512394,
          50.078978086
        ],
        "pixel": [
          5507,
          4131
        ]
      },
      {
        "location": [
          14.937983036,
          50.322910834
        ],
        "pixel": [
          2047,
          1149
        ]
      },
      {
        "location": [
          15.014887333,
          50.323349228
        ],
        "pixel": [
          2651,
          1133
        ]
      },
      {
        "location": [
          14.888887882,
          50.22548731
        ],
        "pixel": [
          1630,
          2364
        ]
      },
      {
        "location": [
          14.981241703,
          50.218897449
        ],
        "pixel": [
          2299,
          2415
        ]
      },
      {
        "location": [
          15.138483524,
          50.264129494
        ],
        "pixel": [
          3595,
          1919
        ]
      },
      {
        "location": [
          15.291948795,
          50.247227393
        ],
        "pixel": [
          4751,
          2139
        ]
      },
      {
        "location": [
          15.231523991,
          50.180658299
        ],
        "pixel": [
          4331,
          2974
        ]
      },
      {
        "location": [
          15.240107059,
          50.091534731
        ],
        "pixel": [
          4351,
          4003
        ]
      },
      {
        "location": [
          15.273409367,
          50.067299658
        ],
        "pixel": [
          4583,
          4307
        ]
      },
      {
        "location": [
          15.157709599,
          50.371109907
        ],
        "pixel": [
          3802,
          546
        ]
      },
      {
        "location": [
          15.006647587,
          50.368482128
        ],
        "pixel": [
          2590,
          578
        ]
      },
      {
        "location": [
          14.96338892,
          50.368920101
        ],
        "pixel": [
          2262,
          594
        ]
      },
      {
        "location": [
          14.795504093,
          50.367387177
        ],
        "pixel": [
          946,
          590
        ]
      },
      {
        "location": [
          15.54806757,
          50.238664302
        ],
        "pixel": [
          6678,
          2234
        ]
      },
      {
        "location": [
          14.825373173,
          50.159767673
        ],
        "pixel": [
          1098,
          3148
        ]
      },
      {
        "location": [
          15.535021305,
          50.179778878
        ],
        "pixel": [
          6614,
          2930
        ]
      },
      {
        "location": [
          15.39357233,
          50.131605861
        ],
        "pixel": [
          5470,
          3482
        ]
      },
      {
        "location": [
          15.561113834,
          50.039524428
        ],
        "pixel": [
          6754,
          4650
        ]
      },
      {
        "location": [
          15.098658085,
          50.029159709
        ],
        "pixel": [
          3230,
          4742
        ]
      },
      {
        "location": [
          15.029306889,
          50.049445998
        ],
        "pixel": [
          2666,
          4442
        ]
      },
      {
        "location": [
          14.792070866,
          50.022101599
        ],
        "pixel": [
          794,
          4778
        ]
      },
      {
        "location": [
          14.809237003,
          50.044154749
        ],
        "pixel": [
          926,
          4490
        ]
      },
      {
        "location": [
          14.795504093,
          50.141288355
        ],
        "pixel": [
          854,
          3370
        ]
      },
      {
        "location": [
          14.985018253,
          50.136007238
        ],
        "pixel": [
          2334,
          3438
        ]
      },
      {
        "location": [
          15.04200983,
          50.185714656
        ],
        "pixel": [
          2790,
          2838
        ]
      },
      {
        "location": [
          14.860392094,
          50.073910438
        ],
        "pixel": [
          1354,
          4170
        ]
      },
      {
        "location": [
          15.072222233,
          50.071045879
        ],
        "pixel": [
          3022,
          4206
        ]
      },
      {
        "location": [
          15.030336857,
          50.089552322
        ],
        "pixel": [
          2706,
          3974
        ]
      },
      {
        "location": [
          15.257273197,
          50.031365155
        ],
        "pixel": [
          4506,
          4762
        ]
      },
      {
        "location": [
          15.35855341,
          50.041288412
        ],
        "pixel": [
          5246,
          4550
        ]
      },
      {
        "location": [
          15.488329411,
          50.057602198
        ],
        "pixel": [
          6222,
          4394
        ]
      },
      {
        "location": [
          15.501375675,
          50.125223147
        ],
        "pixel": [
          6386,
          3602
        ]
      },
      {
        "location": [
          15.490046024,
          50.241299263
        ],
        "pixel": [
          6290,
          2226
        ]
      },
      {
        "location": [
          15.476656437,
          50.291116514
        ],
        "pixel": [
          6150,
          1566
        ]
      },
      {
        "location": [
          15.375032902,
          50.315895985
        ],
        "pixel": [
          5414,
          1310
        ]
      },
      {
        "location": [
          15.169725895,
          50.304933209
        ],
        "pixel": [
          3842,
          1394
        ]
      },
      {
        "location": [
          15.216417789,
          50.37527026
        ],
        "pixel": [
          4234,
          530
        ]
      },
      {
        "location": [
          14.797220707,
          50.207253136
        ],
        "pixel": [
          910,
          2590
        ]
      },
      {
        "location": [
          14.826059818,
          50.290677823
        ],
        "pixel": [
          1166,
          1514
        ]
      },
      {
        "location": [
          14.802370548,
          50.337375693
        ],
        "pixel": [
          962,
          978
        ]
      },
      {
        "location": [
          14.867945194,
          50.330362978
        ],
        "pixel": [
          1466,
          1058
        ]
      },
      {
        "location": [
          14.90983057,
          50.064214315
        ],
        "pixel": [
          1745,
          4273
        ]
      },
      {
        "location": [
          14.871035099,
          50.017027941
        ],
        "pixel": [
          1453,
          4829
        ]
      },
      {
        "location": [
          15.297785282,
          50.206813672
        ],
        "pixel": [
          4835,
          2579
        ]
      },
      {
        "location": [
          15.110674381,
          50.231637026
        ],
        "pixel": [
          3351,
          2275
        ]
      },
      {
        "location": [
          14.960985661,
          50.270932542
        ],
        "pixel": [
          2191,
          1795
        ]
      },
      {
        "location": [
          15.203714848,
          50.245470987
        ],
        "pixel": [
          4163,
          2125
        ]
      },
      {
        "location": [
          15.368853092,
          50.225706957
        ],
        "pixel": [
          5339,
          2379
        ]
      },
      {
        "location": [
          15.142603397,
          50.325102763
        ],
        "pixel": [
          3643,
          1137
        ]
      },
      {
        "location": [
          15.250750065,
          50.27159085
        ],
        "pixel": [
          4479,
          1783
        ]
      },
      {
        "location": [
          15.320787907,
          50.294845224
        ],
        "pixel": [
          5037,
          1511
        ]
      },
      {
        "location": [
          14.77193681,
          50.248999906
        ],
        "pixel": [
          704,
          2030
        ]
      }
    ]
  },
  "pubdate": [null]
}