{
  "date": [
    "1850",
    "1950"
  ],
  "creator": null,
  "georeference_changed": null,
  "created": null,
  "image_url": "http://digitool.is.cuni.cz:5881/ImageServer/imageInfo.jsp?filename=L2V4bGlicmlzL2R0bC9zdG9yYWdlX21hcC8yMDE1LzEwLzAyL3ZpZXdfMS8xMzY2NDkw",
  "description": "Lipsko (Německo)",
  "scale": 50000,
  "external_id": "1366488",
  "title": "Die Umgebungen von Leipzig",
  "collection_id": "1011a696-46e1-5ecc-b44b-76fee1a5d744",
  "is_reviewed": false,
  "contributor": null,
  "catalog_url": null,
  "viewer_url": null,
  "georeference_is_finished": true,
  "bounds": null,
  "reviewed": null,
  "publisher": "Schreibers Erben",
  "link_url": "http://digitool.is.cuni.cz/R/?func=dbin-jump-full&object_id=1366488",
  "id": "5158d335-a690-53c2-a24a-b32d6c6049d4",
  "physical_size": null,
  "dpi": null,
  "georefereces": {
    "cutline": [
      [
        2160,
        0
      ],
      [
        2160,
        2130
      ],
      [
        0,
        2130
      ],
      [
        0,
        0
      ],
      [
        2160,
        0
      ]
    ],
    "created": "2015-11-05T17:41:18.216340+00:00",
    "transformation_method": "affine",
    "mapID": "5158d335-a690-53c2-a24a-b32d6c6049d4",
    "affine_transformation": null,
    "changed": "2015-11-05T17:41:18.216340+00:00",
    "gcps": [
      {
        "location": [
          12.374706048431092,
          51.34054326393718
        ],
        "pixel": [
          1089,
          952
        ]
      },
      {
        "location": [
          12.48019816279359,
          51.395643071232996
        ],
        "pixel": [
          2019,
          184
        ]
      },
      {
        "location": [
          12.487048457479837,
          51.324066998417834
        ],
        "pixel": [
          2041,
          1190
        ]
      },
      {
        "location": [
          12.31657341612616,
          51.375138775015955
        ],
        "pixel": [
          624,
          485
        ]
      },
      {
        "location": [
          12.29066064442379,
          51.3241231639345
        ],
        "pixel": [
          330,
          1184
        ]
      },
      {
        "location": [
          12.33751610411444,
          51.369619999424344
        ],
        "pixel": [
          759,
          548
        ]
      },
      {
        "location": [
          12.307832537409823,
          51.2717002837519
        ],
        "pixel": [
          503,
          1912
        ]
      },
      {
        "location": [
          12.36914197769958,
          51.396702904578746
        ],
        "pixel": [
          1053,
          161
        ]
      },
      {
        "location": [
          12.274602209461136,
          51.384031712417055
        ],
        "pixel": [
          207,
          366
        ]
      },
      {
        "location": [
          12.468860213231677,
          51.28004250227923
        ],
        "pixel": [
          1849,
          1790
        ]
      }
    ]
  },
  "pubdate": [
    "1850",
    "1950"
  ]
}