{
  "date": ["1680"],
  "creator": "Komenský, Jan Amos",
  "georeference_changed": null,
  "created": null,
  "image_url": "https://kramerius.cuni.cz/uk/view/uuid:1741c540-c5c2-11ea-b313-fa163e4ea95f?page=uuid%3Ab46c61ac-1ba4-11ec-b5d9-fa163e4ea95f",
  "description": "Brno (Česko)",
  "scale": 503000,
  "external_id": "788935",
  "title": "Moraviae nova et post omnes priores accuratissima delineatio",
  "collection_id": "1011a696-46e1-5ecc-b44b-76fee1a5d744",
  "is_reviewed": false,
  "contributor": "ze Žerotína, Ladislav Velen",
  "catalog_url": null,
  "viewer_url": null,
  "georeference_is_finished": true,
  "bounds": [
    14.924614,
    48.47272,
    18.896257,
    50.37093
  ],
  "reviewed": null,
  "publisher": "Nicolaum Visscher",
  "link_url": "https://kramerius.cuni.cz/uk/view/uuid:1741c540-c5c2-11ea-b313-fa163e4ea95f",
  "id": "44706608-b1c8-571d-8624-ebf77016814e",
  "physical_size": null,
  "dpi": null,
  "georefereces": {
    "cutline": [
      [
        29,
        188
      ],
      [
        81,
        188
      ],
      [
        83,
        75
      ],
      [
        506,
        86
      ],
      [
        511,
        119
      ],
      [
        574,
        125
      ],
      [
        575,
        301
      ],
      [
        555,
        303
      ],
      [
        535,
        317
      ],
      [
        526,
        337
      ],
      [
        505,
        362
      ],
      [
        488,
        369
      ],
      [
        476,
        390
      ],
      [
        473,
        413
      ],
      [
        192,
        409
      ],
      [
        189,
        382
      ],
      [
        29,
        393
      ],
      [
        29,
        393
      ],
      [
        29,
        188
      ]
    ],
    "created": "2016-07-01T20:35:05.003620+00:00",
    "transformation_method": "affine",
    "mapID": "44706608-b1c8-571d-8624-ebf77016814e",
    "affine_transformation": null,
    "changed": "2016-07-01T20:35:05.003620+00:00",
    "gcps": [
      {
        "location": [
          15.435968762,
          49.082010508
        ],
        "pixel": [
          86,
          341
        ]
      },
      {
        "location": [
          15.483347302,
          49.290698411
        ],
        "pixel": [
          80,
          310
        ]
      },
      {
        "location": [
          15.186029797,
          49.253065082
        ],
        "pixel": [
          27,
          315
        ]
      },
      {
        "location": [
          15.584970837,
          49.283084459
        ],
        "pixel": [
          85,
          304
        ]
      },
      {
        "location": [
          15.58909071,
          49.395829655
        ],
        "pixel": [
          77,
          277
        ]
      },
      {
        "location": [
          15.580850964,
          49.607198504
        ],
        "pixel": [
          74,
          226
        ]
      },
      {
        "location": [
          15.718866711,
          49.486910446
        ],
        "pixel": [
          86,
          255
        ]
      },
      {
        "location": [
          16.734415417,
          48.940592022
        ],
        "pixel": [
          326,
          343
        ]
      },
      {
        "location": [
          16.816812878,
          48.90359492
        ],
        "pixel": [
          341,
          347
        ]
      },
      {
        "location": [
          16.943155652,
          48.905851626
        ],
        "pixel": [
          352,
          346
        ]
      },
      {
        "location": [
          17.029672986,
          48.904948956
        ],
        "pixel": [
          360,
          346
        ]
      },
      {
        "location": [
          17.028299695,
          48.857987647
        ],
        "pixel": [
          357,
          352
        ]
      },
      {
        "location": [
          16.382166272,
          48.752616165
        ],
        "pixel": [
          257,
          371
        ]
      },
      {
        "location": [
          16.232477551,
          48.756690419
        ],
        "pixel": [
          248,
          362
        ]
      },
      {
        "location": [
          16.048456555,
          48.855728781
        ],
        "pixel": [
          218,
          363
        ]
      },
      {
        "location": [
          16.102014905,
          48.801033135
        ],
        "pixel": [
          228,
          376
        ]
      },
      {
        "location": [
          16.159693127,
          48.889149592
        ],
        "pixel": [
          230,
          357
        ]
      },
      {
        "location": [
          16.191278821,
          48.902240848
        ],
        "pixel": [
          235,
          354
        ]
      },
      {
        "location": [
          16.314875012,
          48.94735682
        ],
        "pixel": [
          245,
          341
        ]
      },
      {
        "location": [
          15.728479749,
          48.936532704
        ],
        "pixel": [
          167,
          367
        ]
      },
      {
        "location": [
          15.834223157,
          48.999640291
        ],
        "pixel": [
          174,
          356
        ]
      },
      {
        "location": [
          15.70994032,
          49.096400032
        ],
        "pixel": [
          140,
          326
        ]
      },
      {
        "location": [
          15.492960339,
          48.846692297
        ],
        "pixel": [
          113,
          371
        ]
      },
      {
        "location": [
          15.615869885,
          48.870183763
        ],
        "pixel": [
          131,
          371
        ]
      },
      {
        "location": [
          15.8122505,
          48.894567079
        ],
        "pixel": [
          153,
          367
        ]
      },
      {
        "location": [
          15.351511365,
          48.998288823
        ],
        "pixel": [
          74,
          353
        ]
      },
      {
        "location": [
          15.477854138,
          49.084708862
        ],
        "pixel": [
          81,
          350
        ]
      },
      {
        "location": [
          15.4531349,
          49.18534249
        ],
        "pixel": [
          78,
          325
        ]
      },
      {
        "location": [
          15.324045544,
          49.068516542
        ],
        "pixel": [
          72,
          342
        ]
      },
      {
        "location": [
          16.873804456,
          49.883622653
        ],
        "pixel": [
          269,
          166
        ]
      },
      {
        "location": [
          16.929422742,
          49.744498205
        ],
        "pixel": [
          279,
          189
        ]
      },
      {
        "location": [
          16.848398572,
          49.798600438
        ],
        "pixel": [
          269,
          182
        ]
      },
      {
        "location": [
          16.919123059,
          49.77732152
        ],
        "pixel": [
          277,
          183
        ]
      },
      {
        "location": [
          16.728235608,
          49.708988542
        ],
        "pixel": [
          247,
          194
        ]
      },
      {
        "location": [
          16.743341809,
          49.667231493
        ],
        "pixel": [
          251,
          199
        ]
      },
      {
        "location": [
          16.678797131,
          49.61209285
        ],
        "pixel": [
          250,
          215
        ]
      },
      {
        "location": [
          16.628672009,
          49.436479733
        ],
        "pixel": [
          253,
          234
        ]
      },
      {
        "location": [
          16.639658337,
          49.41191503
        ],
        "pixel": [
          257,
          241
        ]
      },
      {
        "location": [
          16.644464856,
          49.364090277
        ],
        "pixel": [
          259,
          254
        ]
      },
      {
        "location": [
          16.424738293,
          49.34888388
        ],
        "pixel": [
          228,
          258
        ]
      },
      {
        "location": [
          16.353327161,
          49.423975602
        ],
        "pixel": [
          218,
          242
        ]
      },
      {
        "location": [
          16.464563733,
          49.461478432
        ],
        "pixel": [
          229,
          237
        ]
      },
      {
        "location": [
          16.517435437,
          49.506533146
        ],
        "pixel": [
          235,
          230
        ]
      },
      {
        "location": [
          16.537348157,
          49.452105413
        ],
        "pixel": [
          239,
          239
        ]
      },
      {
        "location": [
          16.421991711,
          49.557337182
        ],
        "pixel": [
          216,
          221
        ]
      },
      {
        "location": [
          16.505762463,
          49.563127271
        ],
        "pixel": [
          223,
          214
        ]
      },
      {
        "location": [
          16.599146252,
          49.502074132
        ],
        "pixel": [
          242,
          224
        ]
      },
      {
        "location": [
          16.410318738,
          49.624993772
        ],
        "pixel": [
          182,
          203
        ]
      },
      {
        "location": [
          16.073175793,
          49.561791157
        ],
        "pixel": [
          153,
          223
        ]
      },
      {
        "location": [
          15.987345105,
          49.21091755
        ],
        "pixel": [
          168,
          301
        ]
      },
      {
        "location": [
          15.883661633,
          49.393148247
        ],
        "pixel": [
          136,
          266
        ]
      },
      {
        "location": [
          15.739466077,
          49.576486394
        ],
        "pixel": [
          84,
          230
        ]
      },
      {
        "location": [
          15.484720593,
          49.755589648
        ],
        "pixel": [
          70,
          206
        ]
      },
      {
        "location": [
          16.257883435,
          49.021709078
        ],
        "pixel": [
          230,
          333
        ]
      },
      {
        "location": [
          16.378733044,
          49.101795028
        ],
        "pixel": [
          247,
          317
        ]
      },
      {
        "location": [
          16.465250378,
          49.069866104
        ],
        "pixel": [
          258,
          323
        ]
      },
      {
        "location": [
          15.809503918,
          49.05321895
        ],
        "pixel": [
          151,
          338
        ]
      },
      {
        "location": [
          15.892588025,
          49.094151944
        ],
        "pixel": [
          160,
          326
        ]
      },
      {
        "location": [
          15.768305188,
          49.066267192
        ],
        "pixel": [
          145,
          333
        ]
      },
      {
        "location": [
          15.568491345,
          49.019907911
        ],
        "pixel": [
          123,
          346
        ]
      },
      {
        "location": [
          15.231348401,
          49.024410706
        ],
        "pixel": [
          58,
          355
        ]
      },
      {
        "location": [
          16.391779309,
          48.721822231
        ],
        "pixel": [
          257,
          378
        ]
      },
      {
        "location": [
          16.485849744,
          48.676502763
        ],
        "pixel": [
          270,
          386
        ]
      },
      {
        "location": [
          16.301828748,
          48.772079065
        ],
        "pixel": [
          255,
          365
        ]
      },
      {
        "location": [
          16.31212843,
          49.049168799
        ],
        "pixel": [
          238,
          328
        ]
      },
      {
        "location": [
          16.258570081,
          48.950062482
        ],
        "pixel": [
          239,
          346
        ]
      },
      {
        "location": [
          16.82573927,
          49.717424439
        ],
        "pixel": [
          261,
          194
        ]
      },
      {
        "location": [
          16.664377576,
          49.758251217
        ],
        "pixel": [
          239,
          183
        ]
      },
      {
        "location": [
          16.842905408,
          49.650785369
        ],
        "pixel": [
          264,
          201
        ]
      },
      {
        "location": [
          16.759134656,
          49.647673315
        ],
        "pixel": [
          258,
          202
        ]
      },
      {
        "location": [
          16.660257703,
          49.487802558
        ],
        "pixel": [
          254,
          225
        ]
      },
      {
        "location": [
          16.58266676,
          49.413701968
        ],
        "pixel": [
          250,
          242
        ]
      },
      {
        "location": [
          16.437097913,
          49.275469331
        ],
        "pixel": [
          239,
          273
        ]
      },
      {
        "location": [
          16.41306532,
          49.404766625
        ],
        "pixel": [
          223,
          248
        ]
      },
      {
        "location": [
          16.713816052,
          49.632554793
        ],
        "pixel": [
          251,
          207
        ]
      },
      {
        "location": [
          16.266123181,
          49.71476063
        ],
        "pixel": [
          169,
          195
        ]
      },
      {
        "location": [
          16.261316663,
          49.523473692
        ],
        "pixel": [
          175,
          233
        ]
      },
      {
        "location": [
          16.226297742,
          49.288906999
        ],
        "pixel": [
          184,
          271
        ]
      },
      {
        "location": [
          15.82461012,
          49.197458641
        ],
        "pixel": [
          145,
          307
        ]
      },
      {
        "location": [
          15.882288342,
          49.21540304
        ],
        "pixel": [
          153,
          300
        ]
      },
      {
        "location": [
          15.780664807,
          49.366326116
        ],
        "pixel": [
          126,
          275
        ]
      },
      {
        "location": [
          16.012750989,
          49.356040417
        ],
        "pixel": [
          156,
          266
        ]
      },
      {
        "location": [
          15.27735365,
          49.696109874
        ],
        "pixel": [
          49,
          209
        ]
      },
      {
        "location": [
          15.678354626,
          49.306818193
        ],
        "pixel": [
          120,
          306
        ]
      },
      {
        "location": [
          15.240961438,
          49.261131783
        ],
        "pixel": [
          40,
          303
        ]
      },
      {
        "location": [
          17.817255383,
          49.039267041
        ],
        "pixel": [
          458,
          313
        ]
      },
      {
        "location": [
          17.865320569,
          48.965842588
        ],
        "pixel": [
          458,
          325
        ]
      },
      {
        "location": [
          17.954584485,
          48.895469937
        ],
        "pixel": [
          469,
          332
        ]
      },
      {
        "location": [
          17.791162854,
          48.818668831
        ],
        "pixel": [
          455,
          336
        ]
      },
      {
        "location": [
          17.379862195,
          48.954571593
        ],
        "pixel": [
          383,
          329
        ]
      },
      {
        "location": [
          17.314630872,
          48.903143567
        ],
        "pixel": [
          385,
          337
        ]
      },
      {
        "location": [
          17.228113538,
          48.844884804
        ],
        "pixel": [
          385,
          350
        ]
      },
      {
        "location": [
          17.0962776,
          48.984321505
        ],
        "pixel": [
          355,
          337
        ]
      },
      {
        "location": [
          17.164942151,
          49.106739926
        ],
        "pixel": [
          354,
          315
        ]
      },
      {
        "location": [
          17.115503674,
          48.787010593
        ],
        "pixel": [
          378,
          374
        ]
      },
      {
        "location": [
          16.755701428,
          48.741749872
        ],
        "pixel": [
          324,
          377
        ]
      },
      {
        "location": [
          16.63622511,
          48.807816829
        ],
        "pixel": [
          291,
          365
        ]
      },
      {
        "location": [
          16.6300453,
          48.666980491
        ],
        "pixel": [
          290,
          378
        ]
      },
      {
        "location": [
          16.48790968,
          48.857535882
        ],
        "pixel": [
          277,
          363
        ]
      },
      {
        "location": [
          16.591593152,
          48.854825206
        ],
        "pixel": [
          287,
          360
        ]
      },
      {
        "location": [
          16.402078992,
          48.830422515
        ],
        "pixel": [
          263,
          362
        ]
      },
      {
        "location": [
          17.122713452,
          49.7717786
        ],
        "pixel": [
          325,
          183
        ]
      },
      {
        "location": [
          17.076021558,
          49.701661443
        ],
        "pixel": [
          317,
          193
        ]
      },
      {
        "location": [
          17.250772839,
          49.594292872
        ],
        "pixel": [
          341,
          211
        ]
      },
      {
        "location": [
          17.188288098,
          49.618321308
        ],
        "pixel": [
          337,
          209
        ]
      },
      {
        "location": [
          17.066065198,
          49.601413643
        ],
        "pixel": [
          318,
          207
        ]
      },
      {
        "location": [
          17.078424817,
          49.578267334
        ],
        "pixel": [
          322,
          211
        ]
      },
      {
        "location": [
          17.038599377,
          49.550655457
        ],
        "pixel": [
          322,
          219
        ]
      },
      {
        "location": [
          17.058512097,
          49.513666722
        ],
        "pixel": [
          322,
          225
        ]
      },
      {
        "location": [
          17.164942151,
          49.535952445
        ],
        "pixel": [
          337,
          222
        ]
      },
      {
        "location": [
          17.289911633,
          49.43112121
        ],
        "pixel": [
          353,
          233
        ]
      },
      {
        "location": [
          17.675806409,
          49.399404638
        ],
        "pixel": [
          419,
          230
        ]
      },
      {
        "location": [
          17.898966199,
          49.494492876
        ],
        "pixel": [
          436,
          213
        ]
      },
      {
        "location": [
          17.756830579,
          49.462817288
        ],
        "pixel": [
          423,
          220
        ]
      },
      {
        "location": [
          17.99509657,
          49.338147121
        ],
        "pixel": [
          465,
          238
        ]
      },
      {
        "location": [
          18.142725354,
          49.458354291
        ],
        "pixel": [
          464,
          213
        ]
      },
      {
        "location": [
          17.997156506,
          49.393595159
        ],
        "pixel": [
          465,
          227
        ]
      },
      {
        "location": [
          17.837854749,
          49.574705389
        ],
        "pixel": [
          431,
          198
        ]
      },
      {
        "location": [
          17.807642346,
          49.591622314
        ],
        "pixel": [
          427,
          194
        ]
      },
      {
        "location": [
          18.012262708,
          49.595183025
        ],
        "pixel": [
          450,
          194
        ]
      },
      {
        "location": [
          17.830988293,
          49.662342685
        ],
        "pixel": [
          430,
          180
        ]
      },
      {
        "location": [
          17.958017712,
          49.682783522
        ],
        "pixel": [
          448,
          175
        ]
      },
      {
        "location": [
          18.126245862,
          49.788848761
        ],
        "pixel": [
          464,
          141
        ]
      },
      {
        "location": [
          18.281427747,
          49.83537318
        ],
        "pixel": [
          480,
          134
        ]
      },
      {
        "location": [
          18.15714491,
          49.709432573
        ],
        "pixel": [
          469,
          170
        ]
      },
      {
        "location": [
          18.764826184,
          49.576931635
        ],
        "pixel": [
          562,
          184
        ]
      },
      {
        "location": [
          18.213449841,
          49.109886423
        ],
        "pixel": [
          526,
          285
        ]
      },
      {
        "location": [
          17.830988293,
          48.763027491
        ],
        "pixel": [
          457,
          346
        ]
      },
      {
        "location": [
          18.021875745,
          49.091004449
        ],
        "pixel": [
          478,
          284
        ]
      },
      {
        "location": [
          18.00882948,
          49.140442007
        ],
        "pixel": [
          477,
          277
        ]
      },
      {
        "location": [
          17.875620251,
          49.088756117
        ],
        "pixel": [
          453,
          279
        ]
      },
      {
        "location": [
          17.801462537,
          49.248583011
        ],
        "pixel": [
          435,
          264
        ]
      },
      {
        "location": [
          17.854334241,
          49.223027437
        ],
        "pixel": [
          450,
          267
        ]
      },
      {
        "location": [
          17.997843152,
          49.261579895
        ],
        "pixel": [
          470,
          251
        ]
      },
      {
        "location": [
          17.999216443,
          49.284428183
        ],
        "pixel": [
          470,
          253
        ]
      },
      {
        "location": [
          17.605081921,
          49.292041928
        ],
        "pixel": [
          416,
          251
        ]
      },
      {
        "location": [
          17.511698132,
          49.171427694
        ],
        "pixel": [
          388,
          274
        ]
      },
      {
        "location": [
          17.645594006,
          48.97440684
        ],
        "pixel": [
          440,
          317
        ]
      },
      {
        "location": [
          17.71837843,
          48.987926349
        ],
        "pixel": [
          445,
          316
        ]
      },
      {
        "location": [
          17.780863171,
          49.022609637
        ],
        "pixel": [
          449,
          312
        ]
      },
      {
        "location": [
          17.390161877,
          48.985673352
        ],
        "pixel": [
          384,
          319
        ]
      },
      {
        "location": [
          17.276865369,
          48.881473813
        ],
        "pixel": [
          384,
          343
        ]
      },
      {
        "location": [
          17.133356458,
          48.849403413
        ],
        "pixel": [
          374,
          354
        ]
      },
      {
        "location": [
          17.182794934,
          48.880119142
        ],
        "pixel": [
          375,
          344
        ]
      },
      {
        "location": [
          17.267252332,
          48.973956127
        ],
        "pixel": [
          373,
          329
        ]
      },
      {
        "location": [
          17.173181897,
          48.945552964
        ],
        "pixel": [
          369,
          338
        ]
      },
      {
        "location": [
          17.123056775,
          49.010450715
        ],
        "pixel": [
          354,
          329
        ]
      },
      {
        "location": [
          17.337290173,
          49.087407068
        ],
        "pixel": [
          371,
          309
        ]
      },
      {
        "location": [
          17.013880139,
          48.80284221
        ],
        "pixel": [
          364,
          360
        ]
      },
      {
        "location": [
          16.993967419,
          48.761216981
        ],
        "pixel": [
          368,
          369
        ]
      },
      {
        "location": [
          16.882730847,
          48.759859055
        ],
        "pixel": [
          347,
          369
        ]
      },
      {
        "location": [
          16.96787489,
          48.724993066
        ],
        "pixel": [
          362,
          375
        ]
      },
      {
        "location": [
          16.804453259,
          48.801033135
        ],
        "pixel": [
          333,
          370
        ]
      },
      {
        "location": [
          17.111383801,
          49.47263445
        ],
        "pixel": [
          329,
          234
        ]
      },
      {
        "location": [
          17.107263928,
          49.505641376
        ],
        "pixel": [
          330,
          227
        ]
      },
      {
        "location": [
          17.252832776,
          49.518570453
        ],
        "pixel": [
          343,
          219
        ]
      },
      {
        "location": [
          17.280298596,
          49.481557435
        ],
        "pixel": [
          349,
          227
        ]
      },
      {
        "location": [
          17.450586682,
          49.454783602
        ],
        "pixel": [
          371,
          220
        ]
      },
      {
        "location": [
          17.42792738,
          49.421295731
        ],
        "pixel": [
          370,
          227
        ]
      },
      {
        "location": [
          17.591349011,
          49.426655327
        ],
        "pixel": [
          387,
          225
        ]
      },
      {
        "location": [
          17.460199719,
          49.414595413
        ],
        "pixel": [
          375,
          226
        ]
      },
      {
        "location": [
          17.650400525,
          49.479326841
        ],
        "pixel": [
          413,
          218
        ]
      },
      {
        "location": [
          17.733484631,
          49.549319002
        ],
        "pixel": [
          420,
          206
        ]
      },
      {
        "location": [
          17.586542493,
          49.527485067
        ],
        "pixel": [
          385,
          209
        ]
      },
      {
        "location": [
          17.971063977,
          49.472188258
        ],
        "pixel": [
          448,
          217
        ]
      },
      {
        "location": [
          17.871500378,
          49.530159134
        ],
        "pixel": [
          436,
          209
        ]
      },
      {
        "location": [
          17.814508801,
          49.47888071
        ],
        "pixel": [
          433,
          218
        ]
      },
      {
        "location": [
          17.721125012,
          49.421742387
        ],
        "pixel": [
          425,
          227
        ]
      },
      {
        "location": [
          17.916132336,
          49.368561853
        ],
        "pixel": [
          445,
          232
        ]
      },
      {
        "location": [
          17.930551892,
          49.520799259
        ],
        "pixel": [
          445,
          208
        ]
      },
      {
        "location": [
          17.883173352,
          49.572033759
        ],
        "pixel": [
          433,
          200
        ]
      },
      {
        "location": [
          17.959391003,
          49.576486394
        ],
        "pixel": [
          442,
          195
        ]
      },
      {
        "location": [
          17.98891676,
          49.634333686
        ],
        "pixel": [
          448,
          187
        ]
      },
      {
        "location": [
          18.054834729,
          49.668564719
        ],
        "pixel": [
          456,
          183
        ]
      },
      {
        "location": [
          17.903086072,
          49.712540677
        ],
        "pixel": [
          438,
          172
        ]
      },
      {
        "location": [
          17.928491956,
          49.655230816
        ],
        "pixel": [
          441,
          180
        ]
      },
      {
        "location": [
          17.925745374,
          49.726302747
        ],
        "pixel": [
          442,
          166
        ]
      },
      {
        "location": [
          18.016382581,
          49.756033253
        ],
        "pixel": [
          450,
          166
        ]
      },
      {
        "location": [
          18.082987195,
          49.757364044
        ],
        "pixel": [
          456,
          164
        ]
      },
      {
        "location": [
          18.13105238,
          49.753371562
        ],
        "pixel": [
          461,
          169
        ]
      },
      {
        "location": [
          18.180490857,
          49.778651726
        ],
        "pixel": [
          467,
          165
        ]
      },
      {
        "location": [
          18.222376233,
          49.700107067
        ],
        "pixel": [
          477,
          170
        ]
      },
      {
        "location": [
          18.290354138,
          49.732072777
        ],
        "pixel": [
          485,
          162
        ]
      },
      {
        "location": [
          18.349405652,
          49.686337573
        ],
        "pixel": [
          512,
          174
        ]
      },
      {
        "location": [
          18.376871472,
          49.793281585
        ],
        "pixel": [
          516,
          141
        ]
      },
      {
        "location": [
          18.543039685,
          49.853527718
        ],
        "pixel": [
          524,
          125
        ]
      },
      {
        "location": [
          18.635050183,
          49.748491417
        ],
        "pixel": [
          540,
          138
        ]
      },
      {
        "location": [
          18.447595959,
          49.115729387
        ],
        "pixel": [
          552,
          246
        ]
      },
      {
        "location": [
          18.323999768,
          49.123369149
        ],
        "pixel": [
          545,
          271
        ]
      },
      {
        "location": [
          18.229242688,
          48.997387824
        ],
        "pixel": [
          530,
          311
        ]
      },
      {
        "location": [
          18.039041882,
          48.891858409
        ],
        "pixel": [
          484,
          331
        ]
      },
      {
        "location": [
          17.646280652,
          49.025311217
        ],
        "pixel": [
          434,
          308
        ]
      },
      {
        "location": [
          17.876993542,
          49.28129277
        ],
        "pixel": [
          449,
          250
        ]
      },
      {
        "location": [
          17.730051404,
          49.289802713
        ],
        "pixel": [
          429,
          252
        ]
      },
      {
        "location": [
          17.685419446,
          49.286219758
        ],
        "pixel": [
          422,
          252
        ]
      },
      {
        "location": [
          17.667566663,
          49.227511828
        ],
        "pixel": [
          422,
          263
        ]
      },
      {
        "location": [
          17.57624281,
          49.334120232
        ],
        "pixel": [
          413,
          244
        ]
      },
      {
        "location": [
          17.533670789,
          49.208674653
        ],
        "pixel": [
          386,
          268
        ]
      },
      {
        "location": [
          17.467066174,
          49.068066681
        ],
        "pixel": [
          385,
          303
        ]
      },
      {
        "location": [
          17.526804333,
          48.987926349
        ],
        "pixel": [
          423,
          319
        ]
      }
    ]
  },
  "pubdate": ["1680"]
}