{
  "date": ["1833"],
  "creator": null,
  "georeference_changed": null,
  "created": null,
  "image_url": "https://kramerius.cuni.cz/uk/view/uuid:3d3016ac-4d49-11ec-a784-fa163e4ea95f?page=uuid%3A3de277de-4d49-11ec-a784-fa163e4ea95f",
  "description": "Norsko",
  "scale": 10020000,
  "external_id": "1039863",
  "title": "Europaeisches Russland auch Schweden u. Norwegen dabei Uebersicht des oesterreichischen u. preussischen Staats",
  "collection_id": "1011a696-46e1-5ecc-b44b-76fee1a5d744",
  "is_reviewed": false,
  "contributor": "Thiel, L.",
  "catalog_url": null,
  "viewer_url": null,
  "georeference_is_finished": true,
  "bounds": [
    -2.2694435,
    32.753,
    63.09749,
    72.46354
  ],
  "reviewed": null,
  "publisher": "Justus Perthes",
  "link_url": "https://kramerius.cuni.cz/uk/view/uuid:3d3016ac-4d49-11ec-a784-fa163e4ea95f",
  "id": "c1eb9fdf-c47b-5270-8f32-c3b5d7091677",
  "physical_size": null,
  "dpi": null,
  "georefereces": {
    "cutline": [
      [
        552,
        40
      ],
      [
        550,
        404
      ],
      [
        478,
        405
      ],
      [
        477,
        412
      ],
      [
        466,
        412
      ],
      [
        459,
        409
      ],
      [
        429,
        409
      ],
      [
        427,
        405
      ],
      [
        129,
        405
      ],
      [
        129,
        391
      ],
      [
        105,
        385
      ],
      [
        73,
        385
      ],
      [
        62,
        389
      ],
      [
        47,
        386
      ],
      [
        49,
        74
      ],
      [
        63,
        77
      ],
      [
        70,
        81
      ],
      [
        76,
        82
      ],
      [
        116,
        87
      ],
      [
        157,
        83
      ],
      [
        171,
        74
      ],
      [
        179,
        64
      ],
      [
        183,
        50
      ],
      [
        204,
        47
      ],
      [
        209,
        46
      ],
      [
        212,
        40
      ],
      [
        255,
        40
      ],
      [
        259,
        33
      ],
      [
        294,
        33
      ],
      [
        295,
        40
      ],
      [
        403,
        40
      ],
      [
        406,
        37
      ],
      [
        389,
        34
      ],
      [
        387,
        26
      ],
      [
        424,
        23
      ],
      [
        448,
        28
      ],
      [
        450,
        32
      ],
      [
        448,
        41
      ],
      [
        552,
        40
      ]
    ],
    "created": "2014-08-19T10:01:31.571140+00:00",
    "transformation_method": "affine",
    "mapID": "c1eb9fdf-c47b-5270-8f32-c3b5d7091677",
    "affine_transformation": null,
    "changed": "2020-12-15T04:41:03.712839+00:00",
    "gcps": [
      {
        "location": [
          24.140234673685175,
          65.84666593181913
        ],
        "pixel": [
          255,
          101
        ]
      },
      {
        "location": [
          1.8685545213061867,
          50.953050561290524
        ],
        "pixel": [
          55,
          231
        ]
      },
      {
        "location": [
          28.970858789619573,
          41.008443789837685
        ],
        "pixel": [
          266,
          396
        ]
      },
      {
        "location": [
          37.56858303319158,
          47.10257736898191
        ],
        "pixel": [
          344,
          323
        ]
      },
      {
        "location": [
          39.72620982462916,
          41.00430757350324
        ],
        "pixel": [
          375,
          392
        ]
      },
      {
        "location": [
          8.726090342375867,
          41.92311505905397
        ],
        "pixel": [
          69,
          350
        ]
      },
      {
        "location": [
          56.30915296273013,
          58.021913205854304
        ],
        "pixel": [
          464,
          170
        ]
      },
      {
        "location": [
          -0.34034467226766335,
          53.7478014679877
        ],
        "pixel": [
          55,
          193
        ]
      },
      {
        "location": [
          49.82817591728895,
          40.374706387837364
        ],
        "pixel": [
          474,
          383
        ]
      },
      {
        "location": [
          17.954594953046193,
          40.63871248542574
        ],
        "pixel": [
          154,
          388
        ]
      },
      {
        "location": [
          40.3967751109422,
          56.15959880776845
        ],
        "pixel": [
          360,
          215
        ]
      },
      {
        "location": [
          48.01362399162326,
          46.37978696559378
        ],
        "pixel": [
          433,
          305
        ]
      },
      {
        "location": [
          -3.1937035524113444,
          55.95239955422693
        ],
        "pixel": [
          50,
          161
        ]
      },
      {
        "location": [
          55.960060391249925,
          54.72744660994289
        ],
        "pixel": [
          475,
          207
        ]
      },
      {
        "location": [
          43.28914656382037,
          68.65175504558326
        ],
        "pixel": [
          355,
          65
        ]
      }
    ]
  },
  "pubdate": ["1833"]
}