{
  "date": [null],
  "creator": null,
  "georeference_changed": null,
  "created": null,
  "image_url": "https://kramerius.cuni.cz/uk/view/uuid:7567d4ca-b4ef-11ec-b56e-fa163e4ea95f?page=uuid%3A763d0852-b4ef-11ec-b56e-fa163e4ea95f",
  "description": null,
  "scale": 100000,
  "external_id": "1389867",
  "title": "Lenin",
  "collection_id": "1011a696-46e1-5ecc-b44b-76fee1a5d744",
  "is_reviewed": false,
  "contributor": null,
  "catalog_url": null,
  "viewer_url": null,
  "georeference_is_finished": true,
  "bounds": [
    27.230503,
    52.19436,
    27.956573,
    52.530273
  ],
  "reviewed": null,
  "publisher": null,
  "link_url": "https://kramerius.cuni.cz/uk/view/uuid:7567d4ca-b4ef-11ec-b56e-fa163e4ea95f",
  "id": "87eea710-6d98-57ac-a8a0-dd140cd89a02",
  "physical_size": null,
  "dpi": null,
  "georefereces": {
    "cutline": [
      [
        600,
        0
      ],
      [
        600,
        443
      ],
      [
        0,
        443
      ],
      [
        0,
        0
      ],
      [
        600,
        0
      ]
    ],
    "created": "2016-01-08T13:41:56.242830+00:00",
    "transformation_method": "affine",
    "mapID": "87eea710-6d98-57ac-a8a0-dd140cd89a02",
    "affine_transformation": null,
    "changed": "2016-01-08T13:41:56.242830+00:00",
    "gcps": [
      {
        "location": [
          27.489668423,
          52.336965793
        ],
        "pixel": [
          213,
          258
        ]
      },
      {
        "location": [
          27.509076105,
          52.262673641
        ],
        "pixel": [
          230,
          357
        ]
      },
      {
        "location": [
          27.352562364,
          52.47803073
        ],
        "pixel": [
          100,
          69
        ]
      },
      {
        "location": [
          27.603608662,
          52.466038214
        ],
        "pixel": [
          307,
          82
        ]
      },
      {
        "location": [
          27.621933514,
          52.306603433
        ],
        "pixel": [
          325,
          296
        ]
      }
    ]
  },
  "pubdate": [null]
}