{
  "date": [null],
  "creator": "Reilly, Franz Johann Josef von",
  "georeference_changed": null,
  "created": null,
  "image_url": "https://www.chartae-antiquae.cz/tiles/rajhrad/atlasy/3281002910949/3281002910949_128/ImageProperties.xml",
  "description": null,
  "scale": null,
  "external_id": "58751",
  "title": "mapa z atlasu \"Schauplatz der fünf Theile der Welt :\"",
  "collection_id": "c96b8290-8633-5c89-8aed-95da5c97814e",
  "is_reviewed": false,
  "contributor": null,
  "catalog_url": null,
  "viewer_url": null,
  "georeference_is_finished": true,
  "bounds": [
    9.988824,
    50.333397,
    11.003744,
    50.86022
  ],
  "reviewed": null,
  "publisher": "Albrecht, Ignatz; Herausgegeben von F.I.I. Reilly",
  "link_url": "http://chartae-antiquae.cz/maps/58751",
  "id": "ce746717-6337-59c7-b2e1-3ed0c5169b50",
  "physical_size": null,
  "dpi": null,
  "georefereces": {
    "cutline": [
      [
        969,
        404
      ],
      [
        4425,
        356
      ],
      [
        7977,
        468
      ],
      [
        7945,
        6372
      ],
      [
        5753,
        6292
      ],
      [
        5449,
        6628
      ],
      [
        2937,
        6596
      ],
      [
        2873,
        5428
      ],
      [
        2409,
        5220
      ],
      [
        937,
        5364
      ],
      [
        953,
        1972
      ],
      [
        937,
        1108
      ],
      [
        985,
        436
      ],
      [
        985,
        404
      ],
      [
        969,
        404
      ]
    ],
    "created": "2015-01-17T13:45:09.427430+00:00",
    "transformation_method": "affine",
    "mapID": "ce746717-6337-59c7-b2e1-3ed0c5169b50",
    "affine_transformation": null,
    "changed": "2024-04-17T14:44:43.728763+00:00",
    "gcps": [
      {
        "location": [
          10.860752155,
          50.679244186
        ],
        "pixel": [
          7123,
          2561
        ]
      },
      {
        "location": [
          10.61558726663397,
          50.503816490620665
        ],
        "pixel": [
          5176,
          4687
        ]
      },
      {
        "location": [
          10.657786507696626,
          50.48206803435093
        ],
        "pixel": [
          5588,
          4769
        ]
      },
      {
        "location": [
          10.652419762309199,
          50.45244072683016
        ],
        "pixel": [
          5496,
          5199
        ]
      },
      {
        "location": [
          10.065391242554186,
          50.54408561661853
        ],
        "pixel": [
          978,
          4293
        ]
      },
      {
        "location": [
          10.798439075,
          50.476759206
        ],
        "pixel": [
          6480,
          4999
        ]
      },
      {
        "location": [
          10.531162311,
          50.620033196
        ],
        "pixel": [
          4540,
          3491
        ]
      },
      {
        "location": [
          10.555194904,
          50.711647987
        ],
        "pixel": [
          5272,
          1659
        ]
      },
      {
        "location": [
          10.451452297480689,
          50.36363620750586
        ],
        "pixel": [
          3994,
          6176
        ]
      },
      {
        "location": [
          10.241154817908876,
          50.50098859671536
        ],
        "pixel": [
          2471,
          4540
        ]
      },
      {
        "location": [
          10.1236080381032,
          50.661865041839604
        ],
        "pixel": [
          1806,
          2687
        ]
      },
      {
        "location": [
          10.232569550821053,
          50.81240794322207
        ],
        "pixel": [
          2730,
          1169
        ]
      }
    ]
  },
  "pubdate": ["1791"]
}