{
  "date": [null],
  "creator": null,
  "georeference_changed": null,
  "created": null,
  "image_url": "https://www.chartae-antiquae.cz/tiles/ntm/mapy/2451_120/ImageProperties.xml",
  "description": null,
  "scale": null,
  "external_id": "34342",
  "title": "Generalkarte von Zentraleuropa",
  "collection_id": "ce112fe9-4942-5c37-8f3c-3a397ab0c99b",
  "is_reviewed": false,
  "contributor": null,
  "catalog_url": null,
  "viewer_url": null,
  "georeference_is_finished": true,
  "bounds": [
    24.850729,
    47.291245,
    27.090736,
    48.64638
  ],
  "reviewed": null,
  "publisher": null,
  "link_url": "http://chartae-antiquae.cz/maps/34342",
  "id": "26c0543b-b5c9-5abc-9e81-43d606ac5421",
  "physical_size": null,
  "dpi": null,
  "georefereces": {
    "cutline": [
      [
        544,
        11120
      ],
      [
        12416,
        11120
      ],
      [
        12416,
        560
      ],
      [
        544,
        560
      ],
      [
        544,
        11120
      ]
    ],
    "created": "2015-11-22T08:54:33.884310+00:00",
    "transformation_method": "affine",
    "mapID": "26c0543b-b5c9-5abc-9e81-43d606ac5421",
    "affine_transformation": null,
    "changed": "2015-11-22T08:54:33.884310+00:00",
    "gcps": [
      {
        "location": [
          25.91978538,
          47.844948101
        ],
        "pixel": [
          6356,
          6998
        ]
      },
      {
        "location": [
          25.937638163,
          48.286377656
        ],
        "pixel": [
          5961,
          3090
        ]
      },
      {
        "location": [
          25.62298286,
          47.50976651
        ],
        "pixel": [
          4913,
          10090
        ]
      },
      {
        "location": [
          25.282063365,
          48.580682085
        ],
        "pixel": [
          1917,
          1006
        ]
      },
      {
        "location": [
          26.659989238,
          47.745081418
        ],
        "pixel": [
          10665,
          7370
        ]
      }
    ]
  },
  "pubdate": [null]
}