{
  "date": [null],
  "creator": null,
  "georeference_changed": null,
  "created": null,
  "image_url": "http://chartae-antiquae.cz/tiles/ntm/mapy/3201_1/ImageProperties.xml",
  "description": null,
  "scale": null,
  "external_id": "39249",
  "title": "Rozsah panství Habsburků \u2026 za Karla V. (1555) Říše Napoleonova (1810) a Evropa po kongresu Vídeňském (1815)",
  "collection_id": "ce112fe9-4942-5c37-8f3c-3a397ab0c99b",
  "is_reviewed": false,
  "contributor": null,
  "catalog_url": null,
  "viewer_url": null,
  "georeference_is_finished": true,
  "bounds": null,
  "reviewed": null,
  "publisher": null,
  "link_url": "http://chartae-antiquae.cz/maps/39249",
  "id": "4003a4c8-e9b5-5f67-ba6e-e2449f1bbe8f",
  "physical_size": null,
  "dpi": null,
  "georefereces": {
    "cutline": [
      [
        3968,
        446
      ],
      [
        3951,
        3687
      ],
      [
        265,
        3679
      ],
      [
        298,
        2066
      ],
      [
        1105,
        2042
      ],
      [
        1064,
        437
      ],
      [
        3968,
        446
      ]
    ],
    "created": "2014-11-25T16:02:58.325980+00:00",
    "transformation_method": "affine",
    "mapID": "4003a4c8-e9b5-5f67-ba6e-e2449f1bbe8f",
    "affine_transformation": null,
    "changed": "2014-11-25T16:02:58.325980+00:00",
    "gcps": [
      {
        "location": [
          -7.833849738499374,
          40.144420435965145
        ],
        "pixel": [
          491,
          2615
        ]
      },
      {
        "location": [
          -1.3725489851315826,
          52.81814564988824
        ],
        "pixel": [
          1561,
          1292
        ]
      },
      {
        "location": [
          13.128064324000633,
          43.212354906052184
        ],
        "pixel": [
          2502,
          2806
        ]
      },
      {
        "location": [
          14.929822136500633,
          37.977949099509985
        ],
        "pixel": [
          2511,
          3321
        ]
      },
      {
        "location": [
          9.06312291775063,
          56.07140105599197
        ],
        "pixel": [
          2362,
          1095
        ]
      },
      {
        "location": [
          -7.570177863499384,
          43.499927957566314
        ],
        "pixel": [
          761,
          2236
        ]
      },
      {
        "location": [
          14.90784948025063,
          50.06346209495149
        ],
        "pixel": [
          2695,
          1982
        ]
      },
      {
        "location": [
          6.404431511500629,
          48.03325910031691
        ],
        "pixel": [
          1838,
          1975
        ]
      },
      {
        "location": [
          5.042126824000631,
          52.1193007498629
        ],
        "pixel": [
          1872,
          1657
        ]
      }
    ]
  },
  "pubdate": [null]
}