{
  "date": ["1854"],
  "creator": null,
  "georeference_changed": null,
  "created": null,
  "image_url": "http://digitool.is.cuni.cz:5881/ImageServer/imageInfo.jsp?filename=L2V4bGlicmlzL2R0bC9zdG9yYWdlX21hcC8yMDEyLzExLzEzL3ZpZXdfNC8xMDM4NzM5",
  "description": "Morava (Česko)",
  "scale": null,
  "external_id": "1038737",
  "title": "Die Kronländer Maehren und Schlesien",
  "collection_id": "1011a696-46e1-5ecc-b44b-76fee1a5d744",
  "is_reviewed": false,
  "contributor": null,
  "catalog_url": null,
  "viewer_url": null,
  "georeference_is_finished": true,
  "bounds": null,
  "reviewed": null,
  "publisher": "Marco Berra",
  "link_url": "http://digitool.is.cuni.cz/R/?func=dbin-jump-full&object_id=1038737",
  "id": "12fe620e-cb28-5d1f-bbea-ddc342c94e1c",
  "physical_size": null,
  "dpi": null,
  "georefereces": {
    "cutline": [
      [
        131,
        507
      ],
      [
        739,
        523
      ],
      [
        819,
        195
      ],
      [
        995,
        123
      ],
      [
        1771,
        147
      ],
      [
        1859,
        323
      ],
      [
        1851,
        579
      ],
      [
        2291,
        571
      ],
      [
        2275,
        1267
      ],
      [
        1891,
        1283
      ],
      [
        1707,
        1411
      ],
      [
        1707,
        1699
      ],
      [
        147,
        1707
      ],
      [
        147,
        1707
      ],
      [
        131,
        507
      ]
    ],
    "created": "2015-10-18T14:50:49.334450+00:00",
    "transformation_method": "affine",
    "mapID": "12fe620e-cb28-5d1f-bbea-ddc342c94e1c",
    "affine_transformation": null,
    "changed": "2015-10-18T14:50:49.334450+00:00",
    "gcps": [
      {
        "location": [
          16.447034774,
          49.902447039
        ],
        "pixel": [
          840,
          629
        ]
      },
      {
        "location": [
          16.655088363,
          50.438555652
        ],
        "pixel": [
          916,
          188
        ]
      },
      {
        "location": [
          17.173505722,
          50.465225155
        ],
        "pixel": [
          1202,
          189
        ]
      },
      {
        "location": [
          17.396665512,
          50.263301005
        ],
        "pixel": [
          1333,
          345
        ]
      },
      {
        "location": [
          17.862897811,
          50.353637933
        ],
        "pixel": [
          1600,
          255
        ]
      },
      {
        "location": [
          18.20553392,
          50.342245647
        ],
        "pixel": [
          1757,
          237
        ]
      },
      {
        "location": [
          18.238492904,
          49.946211126
        ],
        "pixel": [
          1820,
          554
        ]
      },
      {
        "location": [
          18.377881942,
          49.866610502
        ],
        "pixel": [
          1880,
          639
        ]
      },
      {
        "location": [
          18.42869371,
          49.899793393
        ],
        "pixel": [
          1906,
          622
        ]
      },
      {
        "location": [
          19.045301376,
          49.821445163
        ],
        "pixel": [
          2236,
          727
        ]
      },
      {
        "location": [
          18.812871872,
          49.337724563
        ],
        "pixel": [
          2132,
          1086
        ]
      },
      {
        "location": [
          19.029851852,
          49.258916063
        ],
        "pixel": [
          2170,
          1163
        ]
      },
      {
        "location": [
          17.163549362,
          48.808746377
        ],
        "pixel": [
          1193,
          1533
        ]
      },
      {
        "location": [
          16.628652511,
          48.667459168
        ],
        "pixel": [
          914,
          1644
        ]
      },
      {
        "location": [
          16.485830246,
          48.676527954
        ],
        "pixel": [
          839,
          1625
        ]
      },
      {
        "location": [
          16.88408464,
          50.342464755
        ],
        "pixel": [
          1041,
          276
        ]
      },
      {
        "location": [
          16.663671432,
          49.759163019
        ],
        "pixel": [
          974,
          736
        ]
      },
      {
        "location": [
          16.947256027,
          50.162016616
        ],
        "pixel": [
          1108,
          432
        ]
      },
      {
        "location": [
          16.934896408,
          50.078366705
        ],
        "pixel": [
          1107,
          505
        ]
      },
      {
        "location": [
          16.918416915,
          49.776902745
        ],
        "pixel": [
          1098,
          736
        ]
      },
      {
        "location": [
          17.076345382,
          49.701464066
        ],
        "pixel": [
          1187,
          790
        ]
      },
      {
        "location": [
          17.298818527,
          49.731653612
        ],
        "pixel": [
          1300,
          766
        ]
      },
      {
        "location": [
          17.250066696,
          49.5943176
        ],
        "pixel": [
          1274,
          875
        ]
      },
      {
        "location": [
          17.112737594,
          49.47265924
        ],
        "pixel": [
          1201,
          973
        ]
      },
      {
        "location": [
          17.392888961,
          49.298336065
        ],
        "pixel": [
          1363,
          1125
        ]
      },
      {
        "location": [
          17.706685958,
          48.901363191
        ],
        "pixel": [
          1560,
          1435
        ]
      },
      {
        "location": [
          15.365911422,
          49.428019947
        ],
        "pixel": [
          280,
          978
        ]
      },
      {
        "location": [
          16.644445358,
          49.363667943
        ],
        "pixel": [
          930,
          1058
        ]
      },
      {
        "location": [
          16.762548385,
          49.382445987
        ],
        "pixel": [
          1009,
          1048
        ]
      },
      {
        "location": [
          17.577596603,
          49.334145092
        ],
        "pixel": [
          1461,
          1095
        ]
      },
      {
        "location": [
          17.876875934,
          49.870593653
        ],
        "pixel": [
          1594,
          638
        ]
      },
      {
        "location": [
          18.054717121,
          49.881213783
        ],
        "pixel": [
          1703,
          628
        ]
      },
      {
        "location": [
          18.092482624,
          49.863512268
        ],
        "pixel": [
          1729,
          640
        ]
      },
      {
        "location": [
          17.910742281,
          49.818787064
        ],
        "pixel": [
          1628,
          698
        ]
      },
      {
        "location": [
          17.865423677,
          49.79175477
        ],
        "pixel": [
          1600,
          701
        ]
      },
      {
        "location": [
          15.390287338,
          49.910849288
        ],
        "pixel": [
          298,
          600
        ]
      },
      {
        "location": [
          15.239911972,
          49.259588259
        ],
        "pixel": [
          227,
          1122
        ]
      },
      {
        "location": [
          15.327115951,
          49.320048395
        ],
        "pixel": [
          260,
          1086
        ]
      },
      {
        "location": [
          15.452085434,
          49.18424541
        ],
        "pixel": [
          334,
          1204
        ]
      },
      {
        "location": [
          15.435605941,
          49.081360885
        ],
        "pixel": [
          331,
          1279
        ]
      },
      {
        "location": [
          15.665632186,
          49.94709484
        ],
        "pixel": [
          404,
          575
        ]
      },
      {
        "location": [
          15.341192184,
          48.666778944
        ],
        "pixel": [
          249,
          1555
        ]
      },
      {
        "location": [
          15.403676925,
          48.724565268
        ],
        "pixel": [
          280,
          1508
        ]
      },
      {
        "location": [
          15.734296737,
          48.866821346
        ],
        "pixel": [
          467,
          1441
        ]
      },
      {
        "location": [
          15.94784349,
          48.75965788
        ],
        "pixel": [
          550,
          1552
        ]
      },
      {
        "location": [
          15.351835189,
          48.997863355
        ],
        "pixel": [
          274,
          1333
        ]
      },
      {
        "location": [
          16.160703598,
          49.953280381
        ],
        "pixel": [
          698,
          590
        ]
      },
      {
        "location": [
          17.005964218,
          50.463913892
        ],
        "pixel": [
          1129,
          176
        ]
      },
      {
        "location": [
          17.331434188,
          50.476587915
        ],
        "pixel": [
          1307,
          164
        ]
      },
      {
        "location": [
          17.382932601,
          50.316822237
        ],
        "pixel": [
          1326,
          310
        ]
      },
      {
        "location": [
          17.702222763,
          50.309806488
        ],
        "pixel": [
          1476,
          311
        ]
      },
      {
        "location": [
          18.219953476,
          50.311999021
        ],
        "pixel": [
          1775,
          274
        ]
      },
      {
        "location": [
          18.121076522,
          50.018621803
        ],
        "pixel": [
          1724,
          503
        ]
      },
      {
        "location": [
          17.902723251,
          49.938256974
        ],
        "pixel": [
          1617,
          588
        ]
      },
      {
        "location": [
          18.108716903,
          49.922344731
        ],
        "pixel": [
          1729,
          592
        ]
      },
      {
        "location": [
          18.282438217,
          49.835619224
        ],
        "pixel": [
          1832,
          652
        ]
      },
      {
        "location": [
          18.633314071,
          49.748737902
        ],
        "pixel": [
          2022,
          767
        ]
      },
      {
        "location": [
          18.764463363,
          49.576288509
        ],
        "pixel": [
          2087,
          886
        ]
      },
      {
        "location": [
          18.78780931,
          49.441192766
        ],
        "pixel": [
          2111,
          1011
        ]
      },
      {
        "location": [
          18.738714157,
          49.221258484
        ],
        "pixel": [
          2019,
          1207
        ]
      },
      {
        "location": [
          18.322606979,
          49.123394115
        ],
        "pixel": [
          1838,
          1258
        ]
      },
      {
        "location": [
          17.828222213,
          48.763505256
        ],
        "pixel": [
          1564,
          1568
        ]
      },
      {
        "location": [
          17.944265304,
          48.867950542
        ],
        "pixel": [
          1624,
          1475
        ]
      },
      {
        "location": [
          17.536397872,
          48.662017114
        ],
        "pixel": [
          1406,
          1650
        ]
      },
      {
        "location": [
          17.227407394,
          48.845813664
        ],
        "pixel": [
          1236,
          1506
        ]
      },
      {
        "location": [
          16.637578903,
          48.806485289
        ],
        "pixel": [
          926,
          1527
        ]
      },
      {
        "location": [
          16.611486373,
          49.912396911
        ],
        "pixel": [
          932,
          614
        ]
      },
      {
        "location": [
          16.741262374,
          50.040456054
        ],
        "pixel": [
          1004,
          512
        ]
      },
      {
        "location": [
          16.972661911,
          49.965428238
        ],
        "pixel": [
          1127,
          581
        ]
      },
      {
        "location": [
          16.928716598,
          49.941129459
        ],
        "pixel": [
          1108,
          591
        ]
      },
      {
        "location": [
          16.927343307,
          49.745410265
        ],
        "pixel": [
          1103,
          763
        ]
      },
      {
        "location": [
          16.999441085,
          49.277734085
        ],
        "pixel": [
          1142,
          1127
        ]
      },
      {
        "location": [
          17.646261154,
          49.024885979
        ],
        "pixel": [
          1503,
          1336
        ]
      },
      {
        "location": [
          15.589071212,
          49.396301371
        ],
        "pixel": [
          389,
          1025
        ]
      },
      {
        "location": [
          16.012044845,
          49.356065266
        ],
        "pixel": [
          607,
          1058
        ]
      },
      {
        "location": [
          17.684026657,
          49.285796755
        ],
        "pixel": [
          1506,
          1132
        ]
      },
      {
        "location": [
          17.996450363,
          49.339514201
        ],
        "pixel": [
          1685,
          1070
        ]
      },
      {
        "location": [
          18.196950851,
          49.337277144
        ],
        "pixel": [
          1810,
          1048
        ]
      },
      {
        "location": [
          17.968199787,
          49.913944484
        ],
        "pixel": [
          1653,
          606
        ]
      },
      {
        "location": [
          17.996916292,
          49.849567758
        ],
        "pixel": [
          1654,
          653
        ]
      },
      {
        "location": [
          15.268064437,
          49.948862218
        ],
        "pixel": [
          232,
          545
        ]
      },
      {
        "location": [
          15.283857284,
          48.815302953
        ],
        "pixel": [
          229,
          1457
        ]
      },
      {
        "location": [
          15.239568649,
          48.931144828
        ],
        "pixel": [
          213,
          1397
        ]
      },
      {
        "location": [
          15.48161119,
          49.290947215
        ],
        "pixel": [
          342,
          1115
        ]
      },
      {
        "location": [
          15.394407211,
          49.314229534
        ],
        "pixel": [
          295,
          1102
        ]
      },
      {
        "location": [
          15.223432479,
          49.431369304
        ],
        "pixel": [
          215,
          978
        ]
      },
      {
        "location": [
          15.579801498,
          49.60833562
        ],
        "pixel": [
          391,
          865
        ]
      },
      {
        "location": [
          15.447278915,
          48.642057885
        ],
        "pixel": [
          298,
          1573
        ]
      },
      {
        "location": [
          15.225492416,
          49.911291471
        ],
        "pixel": [
          197,
          640
        ]
      },
      {
        "location": [
          16.309019027,
          50.081230828
        ],
        "pixel": [
          784,
          463
        ]
      },
      {
        "location": [
          16.046720443,
          48.855527989
        ],
        "pixel": [
          622,
          1475
        ]
      },
      {
        "location": [
          15.818754135,
          48.64183103
        ],
        "pixel": [
          490,
          1589
        ]
      },
      {
        "location": [
          15.653959213,
          48.662243878
        ],
        "pixel": [
          415,
          1553
        ]
      },
      {
        "location": [
          15.62992662,
          48.738831672
        ],
        "pixel": [
          418,
          1514
        ]
      },
      {
        "location": [
          15.488477645,
          48.770067747
        ],
        "pixel": [
          350,
          1490
        ]
      }
    ]
  },
  "pubdate": ["1854"]
}