{
  "date": ["1936"],
  "creator": null,
  "georeference_changed": null,
  "created": null,
  "image_url": "http://digitool.is.cuni.cz:5881/ImageServer/imageInfo.jsp?filename=L2V4bGlicmlzL2R0bC9zdG9yYWdlX21hcC8yMDE1LzA3LzAyL3ZpZXdfMS8xMzMxNjIx",
  "description": "Rachov (Ukrajina : oblast)",
  "scale": 75000,
  "external_id": "1331619",
  "title": "Rachov",
  "collection_id": "1011a696-46e1-5ecc-b44b-76fee1a5d744",
  "is_reviewed": false,
  "contributor": null,
  "catalog_url": null,
  "viewer_url": null,
  "georeference_is_finished": true,
  "bounds": null,
  "reviewed": null,
  "publisher": "Vojenský zeměpisný ústav",
  "link_url": "http://digitool.is.cuni.cz/R/?func=dbin-jump-full&object_id=1331619",
  "id": "d464a6b5-319d-55a7-9e8f-2d6dc76e8d12",
  "physical_size": null,
  "dpi": null,
  "georefereces": {
    "cutline": [
      [
        340,
        1945
      ],
      [
        2668,
        1945
      ],
      [
        2668,
        193
      ],
      [
        340,
        193
      ],
      [
        340,
        1945
      ]
    ],
    "created": "2017-02-25T22:19:33.265750+00:00",
    "transformation_method": "affine",
    "mapID": "d464a6b5-319d-55a7-9e8f-2d6dc76e8d12",
    "affine_transformation": null,
    "changed": "2017-02-25T22:19:33.265750+00:00",
    "gcps": [
      {
        "location": [
          23.84391821,
          48.126469813
        ],
        "pixel": [
          406,
          1050
        ]
      },
      {
        "location": [
          24.244661694,
          48.074767325
        ],
        "pixel": [
          2245,
          1411
        ]
      },
      {
        "location": [
          23.946657544,
          48.234349843
        ],
        "pixel": [
          885,
          303
        ]
      },
      {
        "location": [
          23.894129163,
          48.157970202
        ],
        "pixel": [
          640,
          838
        ]
      },
      {
        "location": [
          24.183979398,
          48.003892984
        ],
        "pixel": [
          1978,
          1905
        ]
      }
    ]
  },
  "pubdate": ["1936"]
}