{
  "date": [null],
  "creator": "Berghaus, Heinrich Karl Wilhelm",
  "georeference_changed": null,
  "created": null,
  "image_url": "http://chartae-antiquae.cz/tiles/rajhrad/atlasy/3281002911106/3281002911106_13/ImageProperties.xml",
  "description": null,
  "scale": null,
  "external_id": "60213",
  "title": "mapa z atlasu \"Vollständiger Hand-Atlas der neueren Erdbeschreibung über alle Theile der Erde in 82 Blättern\"",
  "collection_id": "c96b8290-8633-5c89-8aed-95da5c97814e",
  "is_reviewed": false,
  "contributor": null,
  "catalog_url": null,
  "viewer_url": null,
  "georeference_is_finished": true,
  "bounds": null,
  "reviewed": null,
  "publisher": "herausgegeben von Dr. K. Sohr",
  "link_url": "http://chartae-antiquae.cz/maps/60213",
  "id": "bfd0b001-cab8-5c12-b940-11dd27826df1",
  "physical_size": null,
  "dpi": null,
  "georefereces": {
    "cutline": [
      [
        257,
        8322
      ],
      [
        10098,
        8239
      ],
      [
        10093,
        7320
      ],
      [
        5248,
        7360
      ],
      [
        5219,
        521
      ],
      [
        198,
        562
      ],
      [
        257,
        8322
      ]
    ],
    "created": "2015-01-11T18:47:23.375840+00:00",
    "transformation_method": "affine",
    "mapID": "bfd0b001-cab8-5c12-b940-11dd27826df1",
    "affine_transformation": null,
    "changed": "2015-01-11T18:47:23.375840+00:00",
    "gcps": [
      {
        "location": [
          22.677794424,
          50.021302015
        ],
        "pixel": [
          236,
          1074
        ]
      },
      {
        "location": [
          21.621513692,
          47.533752993
        ],
        "pixel": [
          4712,
          1732
        ]
      },
      {
        "location": [
          15.868554133,
          44.814827698
        ],
        "pixel": [
          10092,
          8033
        ]
      },
      {
        "location": [
          22.766728763,
          49.78542213
        ],
        "pixel": [
          614,
          903
        ]
      },
      {
        "location": [
          16.091610863,
          45.338892066
        ],
        "pixel": [
          9056,
          7879
        ]
      },
      {
        "location": [
          16.613066372,
          49.19481604
        ],
        "pixel": [
          2444,
          7637
        ]
      },
      {
        "location": [
          16.310111828,
          49.872936887
        ],
        "pixel": [
          1285,
          8086
        ]
      },
      {
        "location": [
          19.919531196,
          50.060172605
        ],
        "pixel": [
          611,
          4135
        ]
      },
      {
        "location": [
          18.037271071,
          48.892749626
        ],
        "pixel": [
          2823,
          6037
        ]
      },
      {
        "location": [
          17.10906364,
          48.153866256
        ],
        "pixel": [
          4175,
          6972
        ]
      },
      {
        "location": [
          16.337939791,
          46.308320637
        ],
        "pixel": [
          7423,
          7634
        ]
      },
      {
        "location": [
          18.125298824,
          47.756831871
        ],
        "pixel": [
          4773,
          5761
        ]
      },
      {
        "location": [
          16.068416084,
          45.714741563
        ],
        "pixel": [
          8376,
          7923
        ]
      },
      {
        "location": [
          15.976213347,
          45.812982841
        ],
        "pixel": [
          8191,
          8016
        ]
      }
    ]
  },
  "pubdate": ["1848"]
}