{
  "date": [
    "1601",
    "1650"
  ],
  "creator": "Blaeu, Willem Janszoon",
  "georeference_changed": null,
  "created": null,
  "image_url": "https://kramerius.mzk.cz/search/iiif/uuid:f654e4a8-b024-4c20-9201-978b416c3be8/info.json",
  "description": "Mollova mapová sbírka",
  "scale": null,
  "external_id": "2619320856",
  "title": "Rhenvs Fluviorum Europae celeberrimus, cum Mosa, Mosella, et reliquis in illum se exonerantibus, fluminibus",
  "collection_id": "1b7b2226-02ae-5f6e-a70c-b3710b40b192",
  "is_reviewed": true,
  "contributor": null,
  "catalog_url": null,
  "viewer_url": null,
  "georeference_is_finished": true,
  "bounds": null,
  "reviewed": null,
  "publisher": "Blaeu, Willem Jansz.",
  "link_url": "https://mapy.mzk.cz/mzk03/001/062/882/2619320856",
  "id": "7ad978d8-2edb-58d7-811a-e4b072ce104a",
  "physical_size": [
    40.5,
    95
  ],
  "dpi": null,
  "georefereces": {
    "cutline": [
      [
        327,
        1349
      ],
      [
        326,
        6620
      ],
      [
        4321,
        6621
      ],
      [
        8316,
        6606
      ],
      [
        8520,
        6010
      ],
      [
        9168,
        5578
      ],
      [
        10116,
        5502
      ],
      [
        10424,
        5274
      ],
      [
        10504,
        5122
      ],
      [
        10696,
        5090
      ],
      [
        10968,
        5098
      ],
      [
        11136,
        4898
      ],
      [
        11208,
        4850
      ],
      [
        11276,
        4818
      ],
      [
        11376,
        4822
      ],
      [
        11472,
        4906
      ],
      [
        11736,
        4690
      ],
      [
        11800,
        4730
      ],
      [
        11832,
        4802
      ],
      [
        11856,
        4922
      ],
      [
        12104,
        4778
      ],
      [
        13416,
        5154
      ],
      [
        13784,
        5474
      ],
      [
        13824,
        5914
      ],
      [
        15136,
        5882
      ],
      [
        15140,
        2826
      ],
      [
        14480,
        2866
      ],
      [
        13744,
        2162
      ],
      [
        13536,
        954
      ],
      [
        13624,
        210
      ],
      [
        10300,
        212
      ],
      [
        6976,
        222
      ],
      [
        6944,
        1138
      ],
      [
        6856,
        1190
      ],
      [
        6872,
        1282
      ],
      [
        6628,
        1258
      ],
      [
        6384,
        1314
      ],
      [
        6160,
        1426
      ],
      [
        5096,
        1522
      ],
      [
        4392,
        1406
      ],
      [
        3608,
        1546
      ],
      [
        3328,
        1458
      ],
      [
        2461,
        1439
      ],
      [
        2136,
        1562
      ],
      [
        1859,
        1500
      ],
      [
        1072,
        1458
      ],
      [
        976,
        1330
      ],
      [
        327,
        1349
      ]
    ],
    "created": "2013-04-04T11:56:51.703380+00:00",
    "transformation_method": "affine",
    "mapID": "7ad978d8-2edb-58d7-811a-e4b072ce104a",
    "affine_transformation": null,
    "changed": "2013-04-04T11:56:51.703380+00:00",
    "gcps": [
      {
        "location": [
          7.754204777,
          48.585211548
        ],
        "pixel": [
          5039,
          4313
        ]
      },
      {
        "location": [
          7.594216373,
          47.558893582
        ],
        "pixel": [
          3619,
          4065
        ]
      },
      {
        "location": [
          8.626244572,
          47.698182447
        ],
        "pixel": [
          3483,
          5259
        ]
      },
      {
        "location": [
          8.230522182,
          47.51601429
        ],
        "pixel": [
          3218,
          4860
        ]
      },
      {
        "location": [
          8.083923366,
          47.413715967
        ],
        "pixel": [
          3071,
          4566
        ]
      },
      {
        "location": [
          7.229393032,
          47.1240254
        ],
        "pixel": [
          2595,
          3499
        ]
      },
      {
        "location": [
          6.135566738,
          46.200064219
        ],
        "pixel": [
          1060,
          2057
        ]
      },
      {
        "location": [
          7.675712612,
          46.685749722
        ],
        "pixel": [
          1853,
          4086
        ]
      },
      {
        "location": [
          8.02950671,
          46.756476877
        ],
        "pixel": [
          1875,
          4492
        ]
      },
      {
        "location": [
          8.624570873,
          46.902403385
        ],
        "pixel": [
          1845,
          5381
        ]
      },
      {
        "location": [
          8.646200207,
          46.877063524
        ],
        "pixel": [
          1803,
          5345
        ]
      },
      {
        "location": [
          8.517110851,
          47.17358421
        ],
        "pixel": [
          2419,
          4999
        ]
      },
      {
        "location": [
          8.521574047,
          47.06307894
        ],
        "pixel": [
          2257,
          5075
        ]
      },
      {
        "location": [
          8.536680248,
          47.369497316
        ],
        "pixel": [
          2765,
          5217
        ]
      },
      {
        "location": [
          8.644826916,
          47.269418322
        ],
        "pixel": [
          2539,
          5313
        ]
      },
      {
        "location": [
          9.707410839,
          47.559356951
        ],
        "pixel": [
          3115,
          6530
        ]
      },
      {
        "location": [
          9.18144038,
          47.674145778
        ],
        "pixel": [
          3441,
          5881
        ]
      },
      {
        "location": [
          8.355405834,
          49.633814915
        ],
        "pixel": [
          6759,
          4976
        ]
      },
      {
        "location": [
          8.271635082,
          49.997120996
        ],
        "pixel": [
          7445,
          4690
        ]
      },
      {
        "location": [
          7.404230144,
          50.438677195
        ],
        "pixel": [
          8159,
          3834
        ]
      },
      {
        "location": [
          6.76908305,
          51.225137778
        ],
        "pixel": [
          9369,
          3208
        ]
      },
      {
        "location": [
          6.649778393,
          51.356321425
        ],
        "pixel": [
          9567,
          3058
        ]
      },
      {
        "location": [
          4.466745519,
          51.913894066
        ],
        "pixel": [
          10792,
          869
        ]
      },
      {
        "location": [
          6.175881188,
          49.119279797
        ],
        "pixel": [
          6266,
          2523
        ]
      },
      {
        "location": [
          4.349404138,
          50.847142987
        ],
        "pixel": [
          9010,
          705
        ]
      },
      {
        "location": [
          4.418068688,
          51.214199596
        ],
        "pixel": [
          9614,
          795
        ]
      },
      {
        "location": [
          7.581170109,
          48.036288092
        ],
        "pixel": [
          4291,
          4151
        ]
      },
      {
        "location": [
          8.063366917,
          47.565843677
        ],
        "pixel": [
          3441,
          4703
        ]
      },
      {
        "location": [
          8.223870304,
          47.606020305
        ],
        "pixel": [
          3395,
          4800
        ]
      },
      {
        "location": [
          8.216617611,
          47.491081836
        ],
        "pixel": [
          3142,
          4749
        ]
      },
      {
        "location": [
          7.244499233,
          47.138506721
        ],
        "pixel": [
          2630,
          3528
        ]
      },
      {
        "location": [
          6.926925686,
          46.396941684
        ],
        "pixel": [
          1093,
          3235
        ]
      },
      {
        "location": [
          8.304594067,
          47.053489449
        ],
        "pixel": [
          2319,
          4727
        ]
      },
      {
        "location": [
          8.581655529,
          47.319714256
        ],
        "pixel": [
          2639,
          5233
        ]
      },
      {
        "location": [
          8.853910473,
          47.192484932
        ],
        "pixel": [
          2259,
          5447
        ]
      },
      {
        "location": [
          7.591856029,
          50.359016737
        ],
        "pixel": [
          8039,
          4018
        ]
      },
      {
        "location": [
          6.958940533,
          50.938069207
        ],
        "pixel": [
          8939,
          3510
        ]
      },
      {
        "location": [
          5.107400921,
          52.085072412
        ],
        "pixel": [
          11021,
          1536
        ]
      },
      {
        "location": [
          4.89042094,
          52.372745137
        ],
        "pixel": [
          11533,
          1360
        ]
      },
      {
        "location": [
          4.632242229,
          52.383643309
        ],
        "pixel": [
          11551,
          1076
        ]
      },
      {
        "location": [
          6.566507482,
          53.220124495
        ],
        "pixel": [
          12804,
          2925
        ]
      },
      {
        "location": [
          7.201654577,
          53.359473685
        ],
        "pixel": [
          13008,
          3532
        ]
      },
      {
        "location": [
          6.18480758,
          48.690057581
        ],
        "pixel": [
          5452,
          2526
        ]
      },
      {
        "location": [
          6.129189294,
          49.610268672
        ],
        "pixel": [
          7070,
          2479
        ]
      }
    ]
  },
  "pubdate": [
    "1601",
    "1650"
  ]
}